trove_setup-1.2.0.dist-info/METADATA
trove_setup-1.2.0.dist-info/WHEEL
trove_setup-1.2.0.dist-info/entry_points.txt
trove_setup-1.2.0.dist-info/licenses/LICENSE
trove_setup/__init__.py
trove_setup/__main__.py
trove_setup/app.py
trove_setup/cli.py
trove_setup/guide.py
trove_setup/py.typed
trove_setup/trove_tree.py
trove_setup-1.2.0.dist-info/RECORD
